added_value/__init__.py
added_value/all_items_role.py
added_value/any_items_role.py
added_value/common_options.py
added_value/format_role.py
added_value/grammatical_conjunctions.py
added_value/importer.py
added_value/invoke.py
added_value/items_list_directive.py
added_value/items_table_directive.py
added_value/items_toc_directive.py
added_value/literal_all_items_role.py
added_value/literal_any_items_role.py
added_value/literal_block_directive.py
added_value/literal_format_role.py
added_value/literal_repr_role.py
added_value/literal_str_role.py
added_value/multisort.py
added_value/non_string_iterable.py
added_value/pyobj_role.py
added_value/repr_role.py
added_value/sorted_frozen_set.py
added_value/sphinxext.py
added_value/str_role.py
added_value/tabulator.py
added_value/toposet.py
added_value/toposort.py
added_value/util.py
added_value/version.py
added_value-0.24.0.dist-info/LICENSE.txt
added_value-0.24.0.dist-info/METADATA
added_value-0.24.0.dist-info/WHEEL
added_value-0.24.0.dist-info/top_level.txt
added_value-0.24.0.dist-info/zip-safe
added_value-0.24.0.dist-info/RECORD
