Metadata-Version: 2.1
Name: added-value
Version: 0.24.0
Summary: Sphinx extension for embedding values extracted from Python modules
Home-page: https://github.com/sixty-north/added-value
Author: Sixty North AS
Author-email: systems+added-value@sixty-north.com
License: BSD 3-clause
Keywords: sphinx documentation
Classifier: Development Status :: 5 - Production/Stable
Classifier: Environment :: Console
Classifier: Intended Audience :: Developers
Classifier: Topic :: Documentation
Classifier: Topic :: Utilities
Classifier: License :: OSI Approved :: BSD License
Classifier: Operating System :: OS Independent
Classifier: Programming Language :: Python :: 3 :: Only
Classifier: Programming Language :: Python :: 3.7
Classifier: Programming Language :: Python :: 3.8
Classifier: Programming Language :: Python :: 3.9
Classifier: Programming Language :: Python :: 3.10
License-File: LICENSE.txt
Requires-Dist: docutils
Requires-Dist: les-iterables (>=0.6.0)
Requires-Dist: more-itertools
Requires-Dist: natsort
Requires-Dist: six
Requires-Dist: sphinx
Provides-Extra: dev
Requires-Dist: bumpversion ; extra == 'dev'
Requires-Dist: build ; extra == 'dev'
Requires-Dist: twine ; extra == 'dev'
Requires-Dist: wheel ; extra == 'dev'
Provides-Extra: doc
Requires-Dist: sphinx ; extra == 'doc'
Requires-Dist: sphinx-rtd-theme ; extra == 'doc'
Requires-Dist: better-apidoc ; extra == 'doc'
Provides-Extra: test
Requires-Dist: pytest ; extra == 'test'
Requires-Dist: hypothesis ; extra == 'test'
Requires-Dist: beautifulsoup4 ; extra == 'test'
